npjx/GeoTools.py
npjx/__init__.py
npjx/encoding_tools.py
npjx/geo_tools.py
npjx-0.0.3.dist-info/METADATA
npjx-0.0.3.dist-info/RECORD
npjx-0.0.3.dist-info/WHEEL
npjx-0.0.3.dist-info/top_level.txt
