Metadata-Version: 2.1
Name: npjx
Version: 0.0.3
Summary: npjx
Home-page: UNKNOWN
Author: Li Jing
Author-email: NI9SSaqdy26AtaMRTC@163.com	
License: UNKNOWN
Platform: UNKNOWN
Classifier: Programming Language :: Python :: 3
Classifier: License :: OSI Approved :: MIT License
Classifier: Operating System :: OS Independent
Requires-Python: >=3.6
